impetus/__init__.py
impetus/__main__.py
impetus/metrics.py
impetus/misc/inf_times_v2.py
impetus/misc/layers_times.py
impetus/models/DecoderOnlyLanguageModel.py
impetus/models/__init__.py
impetus-0.1.1.dist-info/LICENSE
impetus-0.1.1.dist-info/METADATA
impetus-0.1.1.dist-info/WHEEL
impetus-0.1.1.dist-info/entry_points.txt
impetus-0.1.1.dist-info/RECORD
