Metadata-Version: 2.1
Name: impetus
Version: 0.1.1
Summary: An awesome tool/library benchmark LLM performance on all kinds of hardware!
Author: Dheemanth Manur
Author-email: dheemanthmanur72@gmail.com
Requires-Python: >=3.10,<4.0
Classifier: Programming Language :: Python :: 3
Classifier: Programming Language :: Python :: 3.10
Classifier: Programming Language :: Python :: 3.11
Classifier: Programming Language :: Python :: 3.12
Requires-Dist: accelerate (>=0.31.0,<0.32.0)
Requires-Dist: bitsandbytes (>=0.43.3,<0.44.0)
Requires-Dist: click (>=8.1.7,<9.0.0)
Requires-Dist: datasets (>=2.20.0,<3.0.0)
Requires-Dist: evaluate (>=0.4.2,<0.5.0)
Requires-Dist: numpy (==1.26.4)
Requires-Dist: torch (==2.3.1)
Requires-Dist: tqdm (>=4.66.5,<5.0.0)
Requires-Dist: transformers (==4.40.2)
